GmoPayment/__init__.py
GmoPayment/_helpers.py
GmoPayment/api.py
GmoPayment/context.py
GmoPayment/errors.py
GmoPayment/exceptions.py
GmoPayment/gateway.py
GmoPayment/response.py
GmoPayment-0.0.3.dist-info/LICENSE
GmoPayment-0.0.3.dist-info/METADATA
GmoPayment-0.0.3.dist-info/WHEEL
GmoPayment-0.0.3.dist-info/top_level.txt
GmoPayment-0.0.3.dist-info/RECORD
