Metadata-Version: 2.1
Name: GmoPayment
Version: 0.0.3
Summary: Python API Client for GMO Payment Gateway
Home-page: https://github.com/blueromans/GmoPayment.git
Author: Yaşar Özyurt
Author-email: blueromans@gmail.com
Project-URL: Bug Tracker, https://github.com/blueromans/GmoPayment/issues
Keywords: GmoPayment
Classifier: Programming Language :: Python :: 3
Classifier: License :: OSI Approved :: MIT License
Classifier: Operating System :: OS Independent
License-File: LICENSE
Requires-Dist: requests
Requires-Dist: six
Requires-Dist: typing
